daplapath/__init__.py
daplapath/path.py
daplapath-2.1.3.dist-info/LICENSE.md
daplapath-2.1.3.dist-info/METADATA
daplapath-2.1.3.dist-info/WHEEL
daplapath-2.1.3.dist-info/RECORD
