Metadata-Version: 2.1
Name: daplapath
Version: 2.1.3
Summary: A pathlib.Path class for dapla
License: MIT
Author: ort
Author-email: ort@ssb.no
Requires-Python: >=3.10,<4
Classifier: License :: OSI Approved :: MIT License
Classifier: Programming Language :: Python :: 3
Classifier: Programming Language :: Python :: 3.10
Classifier: Programming Language :: Python :: 3.11
Classifier: Programming Language :: Python :: 3.12
Requires-Dist: pandas (>=2.0.1)
